MANIFEST.in
RELEASE-VERSION
setup.py
version.py
streamcorpus_elasticsearch/__init__.py
streamcorpus_elasticsearch/indexing.py
streamcorpus_elasticsearch/loader.py
streamcorpus_elasticsearch/manage.py
streamcorpus_elasticsearch/rejester_runner.py
streamcorpus_elasticsearch/writer.py
streamcorpus_elasticsearch.egg-info/PKG-INFO
streamcorpus_elasticsearch.egg-info/SOURCES.txt
streamcorpus_elasticsearch.egg-info/dependency_links.txt
streamcorpus_elasticsearch.egg-info/entry_points.txt
streamcorpus_elasticsearch.egg-info/requires.txt
streamcorpus_elasticsearch.egg-info/top_level.txt