Metadata-Version: 1.1
Name: streamcorpus-elasticsearch
Version: 0.1.1.dev1
Summary: Tool for loading streamcorpus.StreamItems into ElasticSearch
Home-page: https://github.com/trec-kba
Author: Diffeo, Inc.
Author-email: support@diffeo.com
License: MIT/X11 license http://opensource.org/licenses/MIT
Platform: UNKNOWN
Classifier: Development Status :: 3 - Alpha
Classifier: Topic :: Utilities
Classifier: License :: OSI Approved :: MIT License
